temporary_bitcoin_safe_packages_bdkpython-0.31.1.dist-info/WHEEL
temporary_bitcoin_safe_packages_bdkpython-0.31.1.dist-info/METADATA
temporary_bitcoin_safe_packages_bdkpython-0.31.1.dist-info/RECORD
temporary_bitcoin_safe_packages_bdkpython-0.31.1.dist-info/top_level.txt
bdkpython/libbdkffi.so
bdkpython/__init__.py
bdkpython/bdk.py
