Metadata-Version: 2.1
Name: temporary-bitcoin-safe-packages-bdkpython
Version: 0.31.1
Summary: Additional compiled versions for Bitcoin Safe
Home-page: https://github.com/andreasgriffin/bitcoin-safe
Author: Andreas Griffin <AndreasGriffin@proton.me>
License: MIT or Apache 2.0
